tuneapi/__init__.py
tuneapi/apis/__init__.py
tuneapi/apis/compat.py
tuneapi/apis/model_anthropic.py
tuneapi/apis/model_gemini.py
tuneapi/apis/model_openai.py
tuneapi/apis/turbo.py
tuneapi/types/__init__.py
tuneapi/types/bm.py
tuneapi/types/chats.py
tuneapi/types/evals.py
tuneapi/utils/__init__.py
tuneapi/utils/caching.py
tuneapi/utils/code.py
tuneapi/utils/env.py
tuneapi/utils/fs.py
tuneapi/utils/logger.py
tuneapi/utils/logic.py
tuneapi/utils/mime.py
tuneapi/utils/misc.py
tuneapi/utils/networking.py
tuneapi/utils/parallel.py
tuneapi/utils/prompts.py
tuneapi/utils/randomness.py
tuneapi/utils/serdeser.py
tuneapi/utils/subway.py
tuneapi/utils/terminal.py
tuneapi-8.0.33.dist-info/METADATA
tuneapi-8.0.33.dist-info/WHEEL
tuneapi-8.0.33.dist-info/licenses/LICENSE
tuneapi-8.0.33.dist-info/RECORD
